ftpsmartsync/__init__.py
ftpsmartsync-1.4.3.data/data/share/doc/python3-ftpsmartsync/AUTHORS
ftpsmartsync-1.4.3.data/data/share/doc/python3-ftpsmartsync/LICENSE
ftpsmartsync-1.4.3.data/data/share/doc/python3-ftpsmartsync/README.md
ftpsmartsync-1.4.3.data/data/share/man/man1/ftpsmartsync.1
ftpsmartsync-1.4.3.data/scripts/ftpsmartsync
ftpsmartsync-1.4.3.dist-info/licenses/LICENSE
ftpsmartsync-1.4.3.dist-info/METADATA
ftpsmartsync-1.4.3.dist-info/WHEEL
ftpsmartsync-1.4.3.dist-info/top_level.txt
ftpsmartsync-1.4.3.dist-info/RECORD
