Metadata-Version: 2.4
Name: ftpsmartsync
Version: 1.4.3
Summary: Sync local path with FTP remote efficiently by
Home-page: http://github.com/lpenz/ftpsmartsync
Author: "Leandro Lisboa Penz"
Author-email: "lpenz@lpenz.org"
License: GPLv2+
Classifier: Development Status :: 5 - Production/Stable
Classifier: Environment :: Console
Classifier: Operating System :: OS Independent
Classifier: Programming Language :: Python :: 3
Requires-Python: >=3.6
License-File: LICENSE
Provides-Extra: test
Requires-Dist: pytest; extra == "test"
Requires-Dist: pytest-cov; extra == "test"
Requires-Dist: pyftpdlib; extra == "test"
Dynamic: license-file
